pandas_upgrade/__init__.py
pandas_upgrade-0.1.0.dist-info/LICENSE
pandas_upgrade-0.1.0.dist-info/METADATA
pandas_upgrade-0.1.0.dist-info/WHEEL
pandas_upgrade-0.1.0.dist-info/RECORD
