Metadata-Version: 2.1
Name: pandas-upgrade
Version: 0.1.0
Summary: pandas-upgrade
License: UNLICENSED
Author: John Sandall
Author-email: contact@coefficient.ai
Requires-Python: >=3.11.1,<4.0.0
Classifier: Development Status :: 1 - Planning
Classifier: Intended Audience :: Developers
Classifier: License :: OSI Approved :: MIT License
Classifier: License :: Other/Proprietary License
Classifier: Natural Language :: English
Classifier: Operating System :: OS Independent
Classifier: Programming Language :: Python :: 3
Classifier: Programming Language :: Python :: 3
Classifier: Programming Language :: Python :: 3.11
